profi_log/__init__.py
profi_log/master_logger.py
profi_log-0.3.0.dist-info/LICENSE
profi_log-0.3.0.dist-info/METADATA
profi_log-0.3.0.dist-info/WHEEL
profi_log-0.3.0.dist-info/top_level.txt
profi_log-0.3.0.dist-info/RECORD
