Metadata-Version: 2.1
Name: profi-log
Version: 0.3.0
Summary: Продвинутая библиотека для логирования в Python
Home-page: https://github.com/anxnas/profi_log
Author: Святослав Хренов
Author-email: slavakhrenov02@gmail.com
License: UNKNOWN
Platform: UNKNOWN
Classifier: Development Status :: 3 - Alpha
Classifier: Intended Audience :: Developers
Classifier: License :: OSI Approved :: MIT License
Classifier: Operating System :: OS Independent
Classifier: Programming Language :: Python :: 3
Classifier: Programming Language :: Python :: 3.6
Classifier: Programming Language :: Python :: 3.7
Classifier: Programming Language :: Python :: 3.8
Classifier: Programming Language :: Python :: 3.9
Requires-Python: >=3.6
License-File: LICENSE
Requires-Dist: colorlog
